nested_cipher/__init__.py
nested_cipher/b64.py
nested_cipher/test_b64.py
nested_cipher-0.4.dist-info/METADATA
nested_cipher-0.4.dist-info/WHEEL
nested_cipher-0.4.dist-info/top_level.txt
nested_cipher-0.4.dist-info/RECORD
