Metadata-Version: 2.1
Name: nested-cipher
Version: 0.4
Summary: Simple Cipherize Data Encode & Decode.
Home-page: https://github.com/Class-Tooraj/nested_cipher
Author: ToorajJahangiri
Author-email: Toorajjahangiri@gmail.com
License: MIT
Platform: UNKNOWN
Classifier: License :: OSI Approved :: MIT License
Classifier: Operating System :: OS Independent
Classifier: Programming Language :: Python :: 3.10
Classifier: Topic :: Software Development :: Libraries :: Python Modules
Requires-Python: >=3.7.*
